{"nodes":[{"id":"abilitytask_waitattributechangeratiothreshold","label":"AbilityTask WaitAttributeChangeRatioThreshold","file_type":"code","source_file":"AbilityTask__WaitAttributeChangeRatioThreshold Objects.md","source_location":null,"source_url":null,"captured_at":null,"author":null,"contributor":null},{"id":"abilitytask","label":"AbilityTask","file_type":"code","source_file":"AbilityTask__WaitAttributeChangeRatioThreshold Objects.md","source_location":null,"source_url":null,"captured_at":null,"author":null,"contributor":null},{"id":"waitattributechangeratiothresholddelegate","label":"WaitAttributeChangeRatioThresholdDelegate","file_type":"code","source_file":"AbilityTask__WaitAttributeChangeRatioThreshold Objects.md","source_location":null,"source_url":null,"captured_at":null,"author":null,"contributor":null},{"id":"testcamerashake","label":"TestCameraShake","file_type":"code","source_file":"TestCameraShake Objects.md","source_location":null,"source_url":null,"captured_at":null,"author":null,"contributor":null},{"id":"camerashakebase","label":"CameraShakeBase","file_type":"code","source_file":"TestCameraShake Objects.md","source_location":null,"source_url":null,"captured_at":null,"author":null,"contributor":null},{"id":"camerashakepattern","label":"CameraShakePattern","file_type":"code","source_file":"TestCameraShake Objects.md","source_location":null,"source_url":null,"captured_at":null,"author":null,"contributor":null},{"id":"destroysessioncallbackproxy","label":"DestroySessionCallbackProxy","file_type":"code","source_file":"DestroySessionCallbackProxy Objects.md","source_location":null,"source_url":null,"captured_at":null,"author":null,"contributor":null},{"id":"onlineblueprintcallproxybase","label":"OnlineBlueprintCallProxyBase","file_type":"code","source_file":"DestroySessionCallbackProxy Objects.md","source_location":null,"source_url":null,"captured_at":null,"author":null,"contributor":null},{"id":"emptyonlinedelegate","label":"EmptyOnlineDelegate","file_type":"code","source_file":"DestroySessionCallbackProxy Objects.md","source_location":null,"source_url":null,"captured_at":null,"author":null,"contributor":null},{"id":"pcgdynamicmeshbasesettings","label":"PCGDynamicMeshBaseSettings","file_type":"code","source_file":"PCGDynamicMeshBaseSettings Objects.md","source_location":null,"source_url":null,"captured_at":null,"author":null,"contributor":null},{"id":"pcgsettings","label":"PCGSettings","file_type":"code","source_file":"PCGDynamicMeshBaseSettings Objects.md","source_location":null,"source_url":null,"captured_at":null,"author":null,"contributor":null},{"id":"pcgdebugvisualizationsettings","label":"PCGDebugVisualizationSettings","file_type":"code","source_file":"PCGDynamicMeshBaseSettings Objects.md","source_location":null,"source_url":null,"captured_at":null,"author":null,"contributor":null},{"id":"pcgdeterminismsettings","label":"PCGDeterminismSettings","file_type":"code","source_file":"PCGDynamicMeshBaseSettings Objects.md","source_location":null,"source_url":null,"captured_at":null,"author":null,"contributor":null},{"id":"sourceeffectconvolutionreverbpreset","label":"SourceEffectConvolutionReverbPreset","file_type":"code","source_file":"SourceEffectConvolutionReverbPreset Objects.md","source_location":null,"source_url":null,"captured_at":null,"author":null,"contributor":null},{"id":"soundeffectsourcepreset","label":"SoundEffectSourcePreset","file_type":"code","source_file":"SourceEffectConvolutionReverbPreset Objects.md","source_location":null,"source_url":null,"captured_at":null,"author":null,"contributor":null},{"id":"audioimpulseresponse","label":"AudioImpulseResponse","file_type":"code","source_file":"SourceEffectConvolutionReverbPreset Objects.md","source_location":null,"source_url":null,"captured_at":null,"author":null,"contributor":null},{"id":"sourceeffectconvolutionreversettings","label":"SourceEffectConvolutionReverbSettings","file_type":"code","source_file":"SourceEffectConvolutionReverbPreset Objects.md","source_location":null,"source_url":null,"captured_at":null,"author":null,"contributor":null},{"id":"submixeffectconvolutionreverbblocksize","label":"SubmixEffectConvolutionReverbBlockSize","file_type":"code","source_file":"SourceEffectConvolutionReverbPreset Objects.md","source_location":null,"source_url":null,"captured_at":null,"author":null,"contributor":null},{"id":"localplayer","label":"LocalPlayer","file_type":"code","source_file":"LocalPlayer Objects.md","source_location":null,"source_url":null,"captured_at":null,"author":null,"contributor":null},{"id":"player","label":"Player","file_type":"code","source_file":"LocalPlayer Objects.md","source_location":null,"source_url":null,"captured_at":null,"author":null,"contributor":null},{"id":"rigvmfunction_mathdoubleasin","label":"RigVMFunction MathDoubleAsin","file_type":"code","source_file":"RigVMFunction__MathDoubleAsin Objects.md","source_location":null,"source_url":null,"captured_at":null,"author":null,"contributor":null},{"id":"rigvmfunction_mathdoubleunaryop","label":"RigVMFunction MathDoubleUnaryOp","file_type":"code","source_file":"RigVMFunction__MathDoubleAsin Objects.md","source_location":null,"source_url":null,"captured_at":null,"author":null,"contributor":null},{"id":"daysequence","label":"DaySequence","file_type":"code","source_file":"DaySequence Objects.md","source_location":null,"source_url":null,"captured_at":null,"author":null,"contributor":null},{"id":"moviescensequence","label":"MovieSceneSequence","file_type":"code","source_file":"DaySequence Objects.md","source_location":null,"source_url":null,"captured_at":null,"author":null,"contributor":null},{"id":"assetuserdata","label":"AssetUserData","file_type":"code","source_file":"DaySequence Objects.md","source_location":null,"source_url":null,"captured_at":null,"author":null,"contributor":null},{"id":"rigunit_mathvectormax","label":"RigUnit MathVectorMax","file_type":"code","source_file":"RigUnit__MathVectorMax Objects.md","source_location":null,"source_url":null,"captured_at":null,"author":null,"contributor":null},{"id":"rigvmfunction_mathvectormax","label":"RigVMFunction MathVectorMax","file_type":"code","source_file":"RigUnit__MathVectorMax Objects.md","source_location":null,"source_url":null,"captured_at":null,"author":null,"contributor":null},{"id":"updateclusterparams","label":"UpdateClusterParams","file_type":"code","source_file":"UpdateClusterParams Objects.md","source_location":null,"source_url":null,"captured_at":null,"author":null,"contributor":null},{"id":"paramsbase","label":"ParamsBase","file_type":"code","source_file":"UpdateClusterParams Objects.md","source_location":null,"source_url":null,"captured_at":null,"author":null,"contributor":null},{"id":"updateattrparams","label":"UpdateAttrParams","file_type":"code","source_file":"UpdateClusterParams Objects.md","source_location":null,"source_url":null,"captured_at":null,"author":null,"contributor":null},{"id":"modelerembankatom","label":"ModelerEmbankAtom","file_type":"code","source_file":"ModelerEmbankAtom Objects.md","source_location":null,"source_url":null,"captured_at":null,"author":null,"contributor":null},{"id":"entityatombase","label":"EntityAtomBase","file_type":"code","source_file":"ModelerEmbankAtom Objects.md","source_location":null,"source_url":null,"captured_at":null,"author":null,"contributor":null},{"id":"wdpmodelerembankbasetype","label":"WdpModelerEmbankBaseType","file_type":"code","source_file":"ModelerEmbankAtom Objects.md","source_location":null,"source_url":null,"captured_at":null,"author":null,"contributor":null},{"id":"wdpmodelerembanksidetype","label":"WdpModelerEmbankSideType","file_type":"code","source_file":"ModelerEmbankAtom Objects.md","source_location":null,"source_url":null,"captured_at":null,"author":null,"contributor":null},{"id":"wdpmodelerembankfencetype","label":"WdpModelerEmbankFenceType","file_type":"code","source_file":"ModelerEmbankAtom Objects.md","source_location":null,"source_url":null,"captured_at":null,"author":null,"contributor":null},{"id":"hascustomnavigablegeometry","label":"HasCustomNavigableGeometry","file_type":"code","source_file":"HasCustomNavigableGeometry Objects.md","source_location":null,"source_url":null,"captured_at":null,"author":null,"contributor":null},{"id":"dmmaterialpreviewmesh","label":"DMMaterialPreviewMesh","file_type":"code","source_file":"DMMaterialPreviewMesh Objects.md","source_location":null,"source_url":null,"captured_at":null,"author":null,"contributor":null},{"id":"transformconstrainttype","label":"TransformConstraintType","file_type":"code","source_file":"TransformConstraintType Objects.md","source_location":null,"source_url":null,"captured_at":null,"author":null,"contributor":null},{"id":"prefabassetidassets","label":"PrefabAssetIdAssets","file_type":"code","source_file":"PrefabAssetIdAssets Objects.md","source_location":null,"source_url":null,"captured_at":null,"author":null,"contributor":null},{"id":"structbase","label":"StructBase","file_type":"code","source_file":"PrefabAssetIdAssets Objects.md","source_location":null,"source_url":null,"captured_at":null,"author":null,"contributor":null},{"id":"prefabassets","label":"PrefabAssets","file_type":"code","source_file":"PrefabAssetIdAssets Objects.md","source_location":null,"source_url":null,"captured_at":null,"author":null,"contributor":null},{"id":"materialexpressionsubstratetransmittancetomfp","label":"MaterialExpressionSubstrateTransmittanceToMFP","file_type":"code","source_file":"MaterialExpressionSubstrateTransmittanceToMFP Objects.md","source_location":null,"source_url":null,"captured_at":null,"author":null,"contributor":null},{"id":"materialexpressionsubstrateutilitybase","label":"MaterialExpressionSubstrateUtilityBase","file_type":"code","source_file":"MaterialExpressionSubstrateTransmittanceToMFP Objects.md","source_location":null,"source_url":null,"captured_at":null,"author":null,"contributor":null},{"id":"wdpeditableelementcomponent","label":"WdpEditableElementComponent","file_type":"code","source_file":"WdpEditableElementComponent Objects.md","source_location":null,"source_url":null,"captured_at":null,"author":null,"contributor":null},{"id":"primitivecomponent","label":"PrimitiveComponent","file_type":"code","source_file":"WdpEditableElementComponent Objects.md","source_location":null,"source_url":null,"captured_at":null,"author":null,"contributor":null},{"id":"bodyinstance","label":"BodyInstance","file_type":"code","source_file":"WdpEditableElementComponent Objects.md","source_location":null,"source_url":null,"captured_at":null,"author":null,"contributor":null},{"id":"customprimitivedata","label":"CustomPrimitiveData","file_type":"code","source_file":"WdpEditableElementComponent Objects.md","source_location":null,"source_url":null,"captured_at":null,"author":null,"contributor":null},{"id":"posesearchnormalizationsetfactory","label":"PoseSearchNormalizationSetFactory","file_type":"code","source_file":"PoseSearchNormalizationSetFactory Objects.md","source_location":null,"source_url":null,"captured_at":null,"author":null,"contributor":null},{"id":"factory","label":"Factory","file_type":"code","source_file":"PoseSearchNormalizationSetFactory Objects.md","source_location":null,"source_url":null,"captured_at":null,"author":null,"contributor":null},{"id":"assetimporttask","label":"AssetImportTask","file_type":"code","source_file":"PoseSearchNormalizationSetFactory Objects.md","source_location":null,"source_url":null,"captured_at":null,"author":null,"contributor":null},{"id":"automatedassetimportdata","label":"AutomatedAssetImportData","file_type":"code","source_file":"PoseSearchNormalizationSetFactory Objects.md","source_location":null,"source_url":null,"captured_at":null,"author":null,"contributor":null},{"id":"ikrig_bodymover","label":"IKRig BodyMover","file_type":"code","source_file":"IKRig__BodyMover Objects.md","source_location":null,"source_url":null,"captured_at":null,"author":null,"contributor":null},{"id":"ikrigsolver","label":"IKRigSolver","file_type":"code","source_file":"IKRig__BodyMover Objects.md","source_location":null,"source_url":null,"captured_at":null,"author":null,"contributor":null},{"id":"rigvmsimpoint","label":"RigVMSimPoint","file_type":"code","source_file":"RigVMSimPoint Objects.md","source_location":null,"source_url":null,"captured_at":null,"author":null,"contributor":null},{"id":"webjseventargs","label":"WebJSEventArgs","file_type":"code","source_file":"WebJSEventArgs Objects.md","source_location":null,"source_url":null,"captured_at":null,"author":null,"contributor":null},{"id":"eventargsbase","label":"EventArgsBase","file_type":"code","source_file":"WebJSEventArgs Objects.md","source_location":null,"source_url":null,"captured_at":null,"author":null,"contributor":null},{"id":"moviescengroomcachesection","label":"MovieSceneGroomCacheSection","file_type":"code","source_file":"MovieSceneGroomCacheSection Objects.md","source_location":null,"source_url":null,"captured_at":null,"author":null,"contributor":null},{"id":"moviescensection","label":"MovieSceneSection","file_type":"code","source_file":"MovieSceneGroomCacheSection Objects.md","source_location":null,"source_url":null,"captured_at":null,"author":null,"contributor":null},{"id":"moviescengroomcacheparams","label":"MovieSceneGroomCacheParams","file_type":"code","source_file":"MovieSceneGroomCacheSection Objects.md","source_location":null,"source_url":null,"captured_at":null,"author":null,"contributor":null},{"id":"moviescensectionevaloptions","label":"MovieSceneSectionEvalOptions","file_type":"code","source_file":"MovieSceneGroomCacheSection Objects.md","source_location":null,"source_url":null,"captured_at":null,"author":null,"contributor":null},{"id":"moviesceneeasingsettings","label":"MovieSceneEasingSettings","file_type":"code","source_file":"MovieSceneGroomCacheSection Objects.md","source_location":null,"source_url":null,"captured_at":null,"author":null,"contributor":null},{"id":"moviesceneconditioncontainer","label":"MovieSceneConditionContainer","file_type":"code","source_file":"MovieSceneGroomCacheSection Objects.md","source_location":null,"source_url":null,"captured_at":null,"author":null,"contributor":null},{"id":"moviescenetimecodesource","label":"MovieSceneTimecodeSource","file_type":"code","source_file":"MovieSceneGroomCacheSection Objects.md","source_location":null,"source_url":null,"captured_at":null,"author":null,"contributor":null},{"id":"moviesceneinjectionsource","label":"MovieSceneInjectionSource","file_type":"code","source_file":"WdpEditableElementComponent Objects.md","source_location":null,"source_url":null,"captured_at":null,"author":null,"contributor":null}],"edges":[{"source":"abilitytask_waitattributechangeratiothreshold","target":"abilitytask","relation":"implements","confidence":"EXTRACTED","confidence_score":1.0,"source_file":"AbilityTask__WaitAttributeChangeRatioThreshold Objects.md","source_location":null,"weight":1.0},{"source":"abilitytask_waitattributechangeratiothreshold","target":"waitattributechangeratiothresholddelegate","relation":"shares_data_with","confidence":"EXTRACTED","confidence_score":1.0,"source_file":"AbilityTask__WaitAttributeChangeRatioThreshold Objects.md","source_location":null,"weight":1.0},{"source":"testcamerashake","target":"camerashakebase","relation":"implements","confidence":"EXTRACTED","confidence_score":1.0,"source_file":"TestCameraShake Objects.md","source_location":null,"weight":1.0},{"source":"testcamerashake","target":"camerashakepattern","relation":"shares_data_with","confidence":"EXTRACTED","confidence_score":1.0,"source_file":"TestCameraShake Objects.md","source_location":null,"weight":1.0},{"source":"destroysessioncallbackproxy","target":"onlineblueprintcallproxybase","relation":"implements","confidence":"EXTRACTED","confidence_score":1.0,"source_file":"DestroySessionCallbackProxy Objects.md","source_location":null,"weight":1.0},{"source":"destroysessioncallbackproxy","target":"emptyonlinedelegate","relation":"shares_data_with","confidence":"EXTRACTED","confidence_score":1.0,"source_file":"DestroySessionCallbackProxy Objects.md","source_location":null,"weight":1.0},{"source":"pcgdynamicmeshbasesettings","target":"pcgsettings","relation":"implements","confidence":"EXTRACTED","confidence_score":1.0,"source_file":"PCGDynamicMeshBaseSettings Objects.md","source_location":null,"weight":1.0},{"source":"pcgdynamicmeshbasesettings","target":"pcgdebugvisualizationsettings","relation":"shares_data_with","confidence":"EXTRACTED","confidence_score":1.0,"source_file":"PCGDynamicMeshBaseSettings Objects.md","source_location":null,"weight":1.0},{"source":"pcgdynamicmeshbasesettings","target":"pcgdeterminismsettings","relation":"shares_data_with","confidence":"EXTRACTED","confidence_score":1.0,"source_file":"PCGDynamicMeshBaseSettings Objects.md","source_location":null,"weight":1.0},{"source":"sourceeffectconvolutionreverbpreset","target":"soundeffectsourcepreset","relation":"implements","confidence":"EXTRACTED","confidence_score":1.0,"source_file":"SourceEffectConvolutionReverbPreset Objects.md","source_location":null,"weight":1.0},{"source":"sourceeffectconvolutionreverbpreset","target":"audioimpulseresponse","relation":"shares_data_with","confidence":"EXTRACTED","confidence_score":1.0,"source_file":"SourceEffectConvolutionReverbPreset Objects.md","source_location":null,"weight":1.0},{"source":"sourceeffectconvolutionreverbpreset","target":"sourceeffectconvolutionreversettings","relation":"shares_data_with","confidence":"EXTRACTED","confidence_score":1.0,"source_file":"SourceEffectConvolutionReverbPreset Objects.md","source_location":null,"weight":1.0},{"source":"sourceeffectconvolutionreverbpreset","target":"submixeffectconvolutionreverbblocksize","relation":"shares_data_with","confidence":"EXTRACTED","confidence_score":1.0,"source_file":"SourceEffectConvolutionReverbPreset Objects.md","source_location":null,"weight":1.0},{"source":"localplayer","target":"player","relation":"implements","confidence":"EXTRACTED","confidence_score":1.0,"source_file":"LocalPlayer Objects.md","source_location":null,"weight":1.0},{"source":"rigvmfunction_mathdoubleasin","target":"rigvmfunction_mathdoubleunaryop","relation":"implements","confidence":"EXTRACTED","confidence_score":1.0,"source_file":"RigVMFunction__MathDoubleAsin Objects.md","source_location":null,"weight":1.0},{"source":"daysequence","target":"moviescensequence","relation":"implements","confidence":"EXTRACTED","confidence_score":1.0,"source_file":"DaySequence Objects.md","source_location":null,"weight":1.0},{"source":"daysequence","target":"assetuserdata","relation":"shares_data_with","confidence":"EXTRACTED","confidence_score":1.0,"source_file":"DaySequence Objects.md","source_location":null,"weight":1.0},{"source":"rigunit_mathvectormax","target":"rigvmfunction_mathvectormax","relation":"semantically_similar_to","confidence":"EXTRACTED","confidence_score":1.0,"source_file":"RigUnit__MathVectorMax Objects.md","source_location":null,"weight":1.0},{"source":"updateclusterparams","target":"paramsbase","relation":"implements","confidence":"EXTRACTED","confidence_score":1.0,"source_file":"UpdateClusterParams Objects.md","source_location":null,"weight":1.0},{"source":"updateclusterparams","target":"updateattrparams","relation":"shares_data_with","confidence":"EXTRACTED","confidence_score":1.0,"source_file":"UpdateClusterParams Objects.md","source_location":null,"weight":1.0},{"source":"modelerembankatom","target":"entityatombase","relation":"implements","confidence":"EXTRACTED","confidence_score":1.0,"source_file":"ModelerEmbankAtom Objects.md","source_location":null,"weight":1.0},{"source":"modelerembankatom","target":"wdpmodelerembankbasetype","relation":"shares_data_with","confidence":"EXTRACTED","confidence_score":1.0,"source_file":"ModelerEmbankAtom Objects.md","source_location":null,"weight":1.0},{"source":"modelerembankatom","target":"wdpmodelerembanksidetype","relation":"shares_data_with","confidence":"EXTRACTED","confidence_score":1.0,"source_file":"ModelerEmbankAtom Objects.md","source_location":null,"weight":1.0},{"source":"modelerembankatom","target":"wdpmodelerembankfencetype","relation":"shares_data_with","confidence":"EXTRACTED","confidence_score":1.0,"source_file":"ModelerEmbankAtom Objects.md","source_location":null,"weight":1.0},{"source":"prefabassetidassets","target":"structbase","relation":"implements","confidence":"EXTRACTED","confidence_score":1.0,"source_file":"PrefabAssetIdAssets Objects.md","source_location":null,"weight":1.0},{"source":"prefabassetidassets","target":"prefabassets","relation":"shares_data_with","confidence":"EXTRACTED","confidence_score":1.0,"source_file":"PrefabAssetIdAssets Objects.md","source_location":null,"weight":1.0},{"source":"materialexpressionsubstratetransmittancetomfp","target":"materialexpressionsubstrateutilitybase","relation":"implements","confidence":"EXTRACTED","confidence_score":1.0,"source_file":"MaterialExpressionSubstrateTransmittanceToMFP Objects.md","source_location":null,"weight":1.0},{"source":"wdpeditableelementcomponent","target":"primitivecomponent","relation":"implements","confidence":"EXTRACTED","confidence_score":1.0,"source_file":"WdpEditableElementComponent Objects.md","source_location":null,"weight":1.0},{"source":"wdpeditableelementcomponent","target":"bodyinstance","relation":"shares_data_with","confidence":"EXTRACTED","confidence_score":1.0,"source_file":"WdpEditableElementComponent Objects.md","source_location":null,"weight":1.0},{"source":"wdpeditableelementcomponent","target":"customprimitivedata","relation":"shares_data_with","confidence":"EXTRACTED","confidence_score":1.0,"source_file":"WdpEditableElementComponent Objects.md","source_location":null,"weight":1.0},{"source":"wdpeditableelementcomponent","target":"assetuserdata","relation":"shares_data_with","confidence":"EXTRACTED","confidence_score":1.0,"source_file":"WdpEditableElementComponent Objects.md","source_location":null,"weight":1.0},{"source":"wdpeditableelementcomponent","target":"moviesceneinjectionsource","relation":"shares_data_with","confidence":"INFERRED","confidence_score":0.7,"source_file":"WdpEditableElementComponent Objects.md","source_location":null,"weight":1.0},{"source":"posesearchnormalizationsetfactory","target":"factory","relation":"implements","confidence":"EXTRACTED","confidence_score":1.0,"source_file":"PoseSearchNormalizationSetFactory Objects.md","source_location":null,"weight":1.0},{"source":"posesearchnormalizationsetfactory","target":"assetimporttask","relation":"shares_data_with","confidence":"EXTRACTED","confidence_score":1.0,"source_file":"PoseSearchNormalizationSetFactory Objects.md","source_location":null,"weight":1.0},{"source":"posesearchnormalizationsetfactory","target":"automatedassetimportdata","relation":"shares_data_with","confidence":"EXTRACTED","confidence_score":1.0,"source_file":"PoseSearchNormalizationSetFactory Objects.md","source_location":null,"weight":1.0},{"source":"ikrig_bodymover","target":"ikrigsolver","relation":"implements","confidence":"EXTRACTED","confidence_score":1.0,"source_file":"IKRig__BodyMover Objects.md","source_location":null,"weight":1.0},{"source":"rigvmsimpoint","target":"structbase","relation":"implements","confidence":"EXTRACTED","confidence_score":1.0,"source_file":"RigVMSimPoint Objects.md","source_location":null,"weight":1.0},{"source":"webjseventargs","target":"eventargsbase","relation":"implements","confidence":"EXTRACTED","confidence_score":1.0,"source_file":"WebJSEventArgs Objects.md","source_location":null,"weight":1.0},{"source":"moviescengroomcachesection","target":"moviescensection","relation":"implements","confidence":"EXTRACTED","confidence_score":1.0,"source_file":"MovieSceneGroomCacheSection Objects.md","source_location":null,"weight":1.0},{"source":"moviescengroomcachesection","target":"moviescengroomcacheparams","relation":"shares_data_with","confidence":"EXTRACTED","confidence_score":1.0,"source_file":"MovieSceneGroomCacheSection Objects.md","source_location":null,"weight":1.0},{"source":"moviescengroomcachesection","target":"moviescensectionevaloptions","relation":"shares_data_with","confidence":"EXTRACTED","confidence_score":1.0,"source_file":"MovieSceneGroomCacheSection Objects.md","source_location":null,"weight":1.0},{"source":"moviescengroomcachesection","target":"moviesceneeasingsettings","relation":"shares_data_with","confidence":"EXTRACTED","confidence_score":1.0,"source_file":"MovieSceneGroomCacheSection Objects.md","source_location":null,"weight":1.0},{"source":"moviescengroomcachesection","target":"moviesceneconditioncontainer","relation":"shares_data_with","confidence":"EXTRACTED","confidence_score":1.0,"source_file":"MovieSceneGroomCacheSection Objects.md","source_location":null,"weight":1.0},{"source":"moviescengroomcachesection","target":"moviescenetimecodesource","relation":"shares_data_with","confidence":"EXTRACTED","confidence_score":1.0,"source_file":"MovieSceneGroomCacheSection Objects.md","source_location":null,"weight":1.0},{"source":"moviescengroomcachesection","target":"assetuserdata","relation":"shares_data_with","confidence":"EXTRACTED","confidence_score":1.0,"source_file":"MovieSceneGroomCacheSection Objects.md","source_location":null,"weight":1.0},{"source":"daysequence","target":"moviescengroomcachesection","relation":"conceptually_related_to","confidence":"INFERRED","confidence_score":0.8,"source_file":"DaySequence Objects.md","source_location":null,"weight":1.0},{"source":"destroysessioncallbackproxy","target":"emptyonlinedelegate","relation":"conceptually_related_to","confidence":"INFERRED","confidence_score":0.75,"source_file":"DestroySessionCallbackProxy Objects.md","source_location":null,"weight":1.0},{"source":"ikrig_bodymover","target":"rigvmsimpoint","relation":"conceptually_related_to","confidence":"INFERRED","confidence_score":0.75,"source_file":"IKRig__BodyMover Objects.md","source_location":null,"weight":1.0}],"hyperedges":[{"id":"audio_convolution_effects","label":"Audio Convolution Reverb Effects System","nodes":["sourceeffectconvolutionreverbpreset","audioimpulseresponse","sourceeffectconvolutionreversettings","submixeffectconvolutionreverbblocksize"],"relation":"participate_in","confidence":"EXTRACTED","confidence_score":0.9,"source_file":"SourceEffectConvolutionReverbPreset Objects.md"},{"id":"moviescene_timeline_system","label":"MovieScene Timeline and Sequencer System","nodes":["daysequence","moviescengroomcachesection","moviescensection","moviescensequence"],"relation":"participate_in","confidence":"INFERRED","confidence_score":0.85,"source_file":"DaySequence Objects.md"},{"id":"ik_rig_animation_system","label":"Inverse Kinematics Rig Animation System","nodes":["ikrig_bodymover","ikrigsolver","rigvmsimpoint","rigvmfunction_mathdoubleasin","rigvmfunction_mathvectormax"],"relation":"participate_in","confidence":"INFERRED","confidence_score":0.85,"source_file":"IKRig__BodyMover Objects.md"}],"input_tokens":0,"output_tokens":0}